{
  "turnaroundId" : "8f2d4215-d1dc-4398-a765-b145979b6db7",
  "groupBy" : {
    "geography" : [ "country", "division" ],
    "product" : [ "assetType" ]
  },
  "filterBy" : {
    "geography" : {
      "country" : [ "US" ]
    }
  },
  "dateRange" : {
    "end" : "20200630",
    "periodType" : "monthly"
  },
  "attributes" : [ {
    "return" : [ "rank*", "change*", "percent*" ]
  }, {
    "function" : [ "rank", "percent" ],
    "against" : [ "subscriptions", "redemptions" ],
    "by" : {
      "geography" : [ "country" ],
      "product" : [ "assetType" ]
    }
  }, {
    "function" : [ "change" ],
    "against" : [ "percentSubscriptionsCountryAssetType", "rankSubscriptionsCountryAssetType", "percentRedemptionsCountryAssetType", "rankRedemptionsCountryAssetType" ]
  } ]
}

