{
  "turnaroundId" : "f9fff87f-0fbb-4ea5-9182-381f244aa11b",
  "groupBy" : {
    "geography" : [ "cbsaId" ],
    "product" : [ "assetType", "assetClass" ]
  },
  "filterBy" : {
    "geography" : {
      "country" : [ "US" ]
    }
  },
  "dateRange" : {
    "end" : "20200131",
    "periodType" : "monthly"
  },
  "attributes" : [ {
    "return" : [ "percent*", "netFlowRatio", "changeNetFlowRatio" ]
  }, {
    "function" : [ "percent" ],
    "against" : [ "subscriptions", "redemptions" ],
    "by" : {
      "geography" : [ "cbsaId" ],
      "product" : [ "assetType" ]
    }
  }, {
    "function" : [ "change" ],
    "against" : [ "netFlowRatio" ]
  } ]
}
