{
  "turnaroundId": "",
  "dateRange": {
    "end": "20191231",
    "periodType": "monthly"
  },
  "filterBy": {
    "geography": {
      "country": [
        "US"
      ]
    }
  },
  "groupBy": {
    "geography": [
      "division"
    ],
    "product": [
      "assetType"
    ]
  },
  "attributes": [
    {
      "return": [
        "percent*",
        "netFlowRatio",
        "changeNetFlowRatio"
      ]
    },
    {
      "against": [
        "subscriptions",
        "redemptions"
      ],
      "by": {
        "geography": [
          "division"
        ]
      },
      "function": [
        "percent"
      ]
    },
    {
      "against": [
        "netFlowRatio"
      ],
      "function": [
        "change"
      ]
    }
  ]
}