{
    "turnaroundId" : "bdef9d7b-77c9-40e1-830a-1a7483cb45ff",
    "groupBy" : {
      "geography" : [ "cbsaId" ],
      "product" : [ "assetClass" ]
    },
    "filterBy" : {
      "geography" : {
        "country" : [ "US" ]
      }
    },
    "dateRange" : {
      "end" : "20200331",
      "periodType" : "quarterly"
    },
    "attributes" : [ {
      "return" : [ "percent*", "netFlowRatio", "flowIndicator", "changeNetFlowRatio" ]
    }, {
      "function" : [ "percent" ],
      "against" : [ "subscriptions", "redemptions" ],
      "by" : {
        "geography" : [ "cbsaId" ]
      }
    }, {
      "function" : [ "change" ],
      "against" : [ "netFlowRatio" ]
    } ]
  }
